{
  "schemaVersion": "0.1.0",
  "readme": "",
  "modules": [
    {
      "kind": "javascript-module",
      "path": "./fixtures/-TEST/package/my-element.js",
      "declarations": [
        {
          "kind": "mixin",
          "name": "MyMixin",
          "cssParts": [],
          "superclass": {
            "name": "klass",
            "module": "./fixtures/-TEST/package/my-element.js"
          }
        },
        {
          "kind": "function",
          "name": "functionExport",
          "description": "This is a function export",
          "return": {
            "type": {
              "type": "boolean"
            }
          },
          "parameters": [
            {
              "name": "a",
              "type": {
                "type": "string"
              }
            },
            {
              "name": "b",
              "type": {
                "type": "boolean"
              }
            }
          ]
        }
      ],
      "exports": [
        {
          "kind": "js",
          "name": "MyMixin",
          "declaration": {
            "name": "MyMixin",
            "module": "./fixtures/-TEST/package/my-element.js"
          }
        },
        {
          "kind": "js",
          "name": "functionExport",
          "declaration": {
            "name": "functionExport",
            "module": "./fixtures/-TEST/package/my-element.js"
          }
        }
      ]
    }
  ]
}